views_stepshifter/__init__.py
views_stepshifter/manager/__init__.py
views_stepshifter/manager/stepshifter_manager.py
views_stepshifter/models/__init__.py
views_stepshifter/models/darts_model.py
views_stepshifter/models/hurdle_model.py
views_stepshifter/models/shurf_model.py
views_stepshifter/models/stepshifter.py
views_stepshifter/models/validation.py
views_stepshifter-1.1.0.dist-info/METADATA
views_stepshifter-1.1.0.dist-info/WHEEL
views_stepshifter-1.1.0.dist-info/RECORD
