Metadata-Version: 2.4
Name: views_stepshifter
Version: 1.1.0
Summary: 
Author: Xiaolong Sun
Author-email: xiaolong.sun@pcr.uu.se
Requires-Python: >=3.11,<3.15
Classifier: Programming Language :: Python :: 3
Classifier: Programming Language :: Python :: 3.11
Classifier: Programming Language :: Python :: 3.12
Classifier: Programming Language :: Python :: 3.13
Classifier: Programming Language :: Python :: 3.14
Requires-Dist: darts (>=0.38.0,<0.39.0)
Requires-Dist: lightgbm (==4.6.0)
Requires-Dist: numpy (>=1.25.2,<2.0.0)
Requires-Dist: pandas (>=1.5.3,<2.0.0)
Requires-Dist: scikit-learn (>=1.6.0,<2.0.0)
Requires-Dist: scipy (==1.15.1)
Requires-Dist: views_forecasts (>=0.5.5,<0.6.0)
Requires-Dist: views_pipeline_core (>=2.0.0,<3.0.0)
Requires-Dist: xgboost (>=3.0.0,<4.0.0)
